gentests.py
gentests-1.0.0.dist-info/DESCRIPTION.rst
gentests-1.0.0.dist-info/METADATA
gentests-1.0.0.dist-info/RECORD
gentests-1.0.0.dist-info/WHEEL
gentests-1.0.0.dist-info/metadata.json
gentests-1.0.0.dist-info/top_level.txt
