Metadata-Version: 2.0
Name: gentests
Version: 1.0.0
Summary: A module for generating tests from data with unittest
Home-page: https://github.com/jaredwindover/GenTests
Author: Jared Windover
Author-email: jaredwindover@gmail.com
License: MIT
Keywords: test generation testing unit unittest data theory
Platform: UNKNOWN
Classifier: Development Status :: 5 - Production/Stable
Classifier: Intended Audience :: Developers
Classifier: Topic :: Software Development :: Testing
Classifier: License :: OSI Approved :: MIT License
Classifier: Programming Language :: Python :: 3
